bakesite/__init__.py
bakesite/boilerplate/bakesite.yaml
bakesite/boilerplate/content/blog/2025-01-31-Getting-Started.md
bakesite/boilerplate/content/blog/2025-02-14-Happy-Valentines-Day.md
bakesite/boilerplate/content/home.md
bakesite/boilerplate.py
bakesite/compile.py
bakesite/layouts/basic/static/css/style.css
bakesite/layouts/basic/templates/feed.xml
bakesite/layouts/basic/templates/item.html
bakesite/layouts/basic/templates/item.xml
bakesite/layouts/basic/templates/list.html
bakesite/layouts/basic/templates/page.html
bakesite/layouts/basic/templates/post.html
bakesite/logging.py
bakesite/parameters.py
bakesite/server.py
bakesite-0.6.1.dist-info/WHEEL
bakesite-0.6.1.dist-info/entry_points.txt
bakesite-0.6.1.dist-info/METADATA
bakesite-0.6.1.dist-info/RECORD
