Metadata-Version: 2.3
Name: bakesite
Version: 0.6.1
Summary: The Simplest Static Site Generator
Author: Andrew Graham-Yooll
Author-email: Andrew Graham-Yooll <andrewgy8@gmail.com>
Classifier: Development Status :: 4 - Beta
Classifier: Environment :: Console
Classifier: Intended Audience :: Developers
Classifier: License :: OSI Approved :: MIT License
Classifier: Programming Language :: Python :: 3
Classifier: Programming Language :: Python :: 3.9
Classifier: Programming Language :: Python :: 3.10
Classifier: Programming Language :: Python :: 3.11
Classifier: Programming Language :: Python :: 3.12
Classifier: Programming Language :: Python :: 3.13
Requires-Dist: click>=8.1.8
Requires-Dist: jinja2>=3.1.5
Requires-Dist: markdown-it-py[plugins]
Requires-Dist: pyyaml>=6.0.2
Requires-Python: >=3.9
